{
  "$type": "GameMaster.Game, GameMaster",
  "Players": [
    {
      "$type": "GameMaster.Player, GameMaster",
      "Name": "Peter",
      "Points": 0
    }
  ],
  "Levels": [
    {
      "$type": "GameMaster.TestLevel, GameMaster",
      "Name": "Sound",
      "Beschreibung": "Spielt Sound"
    },
    {
      "$type": "WebGameController.Models.FirstLevel, GameMaster",
      "Name": "Bzzer to .2",
      "Beschreibung": "Setzt auf BuzzerPress dot2 Values"
    }
  ],
  "LevelID": 0,
  "CLevel": {
    "$type": "GameMaster.TestLevel, GameMaster",
    "Name": "Sound",
    "Beschreibung": "Spielt Sound"
  }
}